stored_messages/__init__.py
stored_messages/admin.py
stored_messages/api.py
stored_messages/compat.py
stored_messages/constants.py
stored_messages/models.py
stored_messages/serializers.py
stored_messages/settings.py
stored_messages/storage.py
stored_messages/urls.py
stored_messages/views.py
stored_messages/backends/__init__.py
stored_messages/backends/base.py
stored_messages/backends/exceptions.py
stored_messages/backends/signals.py
stored_messages/backends/default/__init__.py
stored_messages/backends/default/backend.py
stored_messages/backends/redis/__init__.py
stored_messages/backends/redis/backend.py
stored_messages/migrations/0001_initial.py
stored_messages/migrations/__init__.py
stored_messages/static/js/stored_messages.js
stored_messages/templates/stored_messages/base.html
stored_messages/templates/stored_messages/stored_messages_list.html
stored_messages/templatetags/__init__.py
stored_messages/templatetags/stored_messages_tags.py
stored_messages/tests/__init__.py
stored_messages/tests/base.py
stored_messages/tests/settings.py
stored_messages/tests/test_api.py
stored_messages/tests/test_default_backend.py
stored_messages/tests/test_models.py
stored_messages/tests/test_redis_backend.py
stored_messages/tests/test_restapi.py
stored_messages/tests/test_storage.py
stored_messages/tests/test_templatetags.py
stored_messages/tests/urls.py
stored_messages/tests/views.py
django3_stored_messages-2.0.2.dist-info/AUTHORS.rst
django3_stored_messages-2.0.2.dist-info/LICENSE
django3_stored_messages-2.0.2.dist-info/METADATA
django3_stored_messages-2.0.2.dist-info/WHEEL
django3_stored_messages-2.0.2.dist-info/top_level.txt
django3_stored_messages-2.0.2.dist-info/RECORD
